LICENSE.rst
MANIFEST.in
README.rst
setup.cfg
setup.py
minimo/__init__.py
minimo/__main__.py
minimo/app.py
minimo/attribute_dict.py
minimo/callbacks.py
minimo/counter.py
minimo/globals.py
minimo/logger.py
minimo/performer.py
minimo/reporter.py
minimo/runtime_context.py
minimo/scheduler.py
minimo/timer.py
minimo/utils.py
minimo.egg-info/PKG-INFO
minimo.egg-info/SOURCES.txt
minimo.egg-info/dependency_links.txt
minimo.egg-info/entry_points.txt
minimo.egg-info/not-zip-safe
minimo.egg-info/requires.txt
minimo.egg-info/top_level.txt
minimo/bin/minimo
minimo/commands/__init__.py
minimo/commands/common.py
minimo/commands/init.py
minimo/commands/ls.py
minimo/commands/new.py
minimo/commands/run.py
minimo/commands/start.py
minimo/commands/version.py
minimo/interface/__init__.py
minimo/interface/api.py
minimo/interface/cli.py
minimo/templates/project/.dockerignore.mot
minimo/templates/project/.gitignore.mot
minimo/templates/project/Dockerfile.mot
minimo/templates/project/README.md.mot
minimo/templates/project/config.yml.mot
minimo/templates/project/requirements.txt.mot
minimo/templates/project/bin/minimo
minimo/templates/project/cases/__init__.py
minimo/templates/project/ext/__init__.py
minimo/templates/project/lib/__init__.py
minimo/templates/project/lib/app.py.mot
minimo/templates/project/lib/performer.py
minimo/templates/project/log/.placeholder
minimo/templates/project/templates/README.md.mako
minimo/templates/project/templates/__init__.py.mako
minimo/templates/project/templates/__main__.py.mako
minimo/templates/project/templates/config.yml.mako
minimo/templates/project/templates/performer.py.mako
minimo/templates/project/vendor/__init__.py
minimo/templates/reports/report.html.mako
minimo/templates/reports/report.txt.mako
minimo/templates/reports/report.xml.mako
test/test-api.py