Metadata-Version: 1.1
Name: minimo
Version: 0.8.5
Summary: A lightweight automation framework.
Home-page: https://github.com/philip1134/mini-mo
Author: Philip CHAN
Author-email: philip1134@imior.com
License: MIT
Keywords: Python Automation
Platform: any
Classifier: Development Status :: 4 - Beta
Classifier: Environment :: Console
Classifier: Intended Audience :: Developers
Classifier: License :: OSI Approved :: MIT License
Classifier: Operating System :: OS Independent
Classifier: Programming Language :: Python
Classifier: Programming Language :: Python :: 3
Classifier: Programming Language :: Python :: 3.8
Classifier: Topic :: Software Development :: Libraries :: Application Frameworks
Classifier: Topic :: Software Development :: Testing
